<xml xmlns="https://developers.google.com/blockly/xml"><block type="variables_def" id="__2*CMElF!$X0Z=j}.eG" x="88" y="-64"><mutation xmlns="http://www.w3.org/1999/xhtml" no_input="false" variable_uuid="365a594e-a113-4f6a-a43d-85a9c24d0059" variable_name="loc_points" variable_scope="APP"/><field name="SCOPE">APP</field><field name="NAME">loc_points</field><value name="VALUE"><block type="lists_create_empty" id="Y2Oc_7]^syV6M^RbW(uH"/></value></block><block type="component_event" id="zpgmw8r,/v-tQ#9$r_Ib" x="92" y="-17"><mutation xmlns="http://www.w3.org/1999/xhtml" component_id="06028a38-f9c7-4ca2-87c9-7242635840d6" component_name="Map" component_type="Screen" parent_id="undefined" event_id="Opens" was_updated="true"/><field name="component_id">06028a38-f9c7-4ca2-87c9-7242635840d6</field><field name="event_id">Opens</field><statement name="input_do"><block type="controls_if" id="cxl+xabvk+ugKY(N:P-I"><value name="IF0"><block type="logic_compare" id="z{sI}_yIWHu//nWyYM^@"><field name="OP">EQ</field><value name="A"><block type="variables_get_dynamic" id="GsP3JGXD6HB:dQ{RzM]/"><field name="SCOPE">CLOUD</field><value name="NAME"><shadow type="text" id="wlh.*E4uY|}m@6w2$]7G"><field name="TEXT">name</field></shadow><block type="variables_get" id="2`T]~pWsmLYR~FA$R#@!"><mutation xmlns="http://www.w3.org/1999/xhtml" saved_name="app variable userID"/><field name="VAR">f1725fbe-2b54-4de7-b810-bb13dc99a163</field></block></value></block></value><value name="B"><block type="logic_null" id="=+_/8`f*tiHNi,gl?/)_"/></value></block></value><statement name="DO0"><block type="variables_set_dynamic" id="FNyU0^P{;rohj4f4sx-w"><field name="SCOPE">CLOUD</field><value name="NAME"><shadow type="text" id="Tx9s!/j).=yC?FB5#e}N"><field name="TEXT">name</field></shadow><block type="variables_get" id="kA0Ek99?3$Npvo%gjTX|"><mutation xmlns="http://www.w3.org/1999/xhtml" saved_name="app variable userID"/><field name="VAR">f1725fbe-2b54-4de7-b810-bb13dc99a163</field></block></value><value name="VALUE"><block type="object_create" id="wN$Qqy=bMugjvjy_!Iyf"><mutation xmlns="http://www.w3.org/1999/xhtml" num_fields="3"><field name="name"/><field name="bio"/><field name="image"/></mutation><field name="field1">name</field><field name="field2">bio</field><field name="field3">image</field><value name="field_input1"><block type="text" id="_,I17A!fClg{DMd=ciGt"><field name="TEXT"/></block></value><value name="field_input2"><block type="text" id="RBn3C#hh!Emp]r_EwihN"><field name="TEXT"/></block></value><value name="field_input3"><block type="text" id="g/{]6Onw7Ki@zC$P:PWX"><field name="TEXT"/></block></value></block></value><next><block type="location_get_current_location" id="b)ZAc7dafbpjWCh!@lWQ"><mutation xmlns="http://www.w3.org/1999/xhtml" show_callback_params="true" callback_params_added="true"/><value name="CALLBACK_PARAM0"><block type="callback_arg" id="5)]b)ojY[~#}W#a7{T5q"><mutation xmlns="http://www.w3.org/1999/xhtml" tooltip="" language_neutral_name="latitude" arg_name_trans_key="blocks.location.get_current_location.latitude" old_arg_name="latitude"/></block></value><value name="CALLBACK_PARAM1"><block type="callback_arg" id=",h-!:U4%dTC8%rsPIov@"><mutation xmlns="http://www.w3.org/1999/xhtml" tooltip="" language_neutral_name="longitude" arg_name_trans_key="blocks.location.get_current_location.longitude" old_arg_name="longitude"/></block></value><value name="CALLBACK_PARAM2"><block type="callback_arg" id="UI`AE*JP=4_qKT4mlAt+"><mutation xmlns="http://www.w3.org/1999/xhtml" tooltip="" language_neutral_name="location" arg_name_trans_key="blocks.location.get_current_location.location" old_arg_name="location"/></block></value><value name="CALLBACK_PARAM3"><block type="callback_arg" id="VWD)ON]LaSmM*jv-=MOK"><mutation xmlns="http://www.w3.org/1999/xhtml" tooltip="" language_neutral_name="error" arg_name_trans_key="blocks.location.error" old_arg_name="error"/></block></value><statement name="DO"><block type="lists_setIndex" id="QIot4J{ilJ^jz`H.*-pV"><mutation at="false"/><field name="MODE">INSERT</field><field name="WHERE">LAST</field><value name="LIST"><block type="variables_get" id="^iT_FZE8wal:-h_6:,7y"><mutation xmlns="http://www.w3.org/1999/xhtml" saved_name="app variable loc_points"/><field name="VAR">365a594e-a113-4f6a-a43d-85a9c24d0059</field></block></value><value name="TO"><shadow type="text" id="%U.0FOSdcc;9u}rMzM`D"><field name="TEXT">abc</field></shadow><block type="object_create" id="Fh|C`b]tKg!;M;4:R9=t"><mutation xmlns="http://www.w3.org/1999/xhtml" num_fields="2"><field name="latitude"/><field name="longitude"/></mutation><field name="field1">latitude</field><field name="field2">longitude</field><value name="field_input1"><block type="callback_arg" id="xKa{3uRv^yEjst$~v$/_"><mutation xmlns="http://www.w3.org/1999/xhtml" tooltip="" language_neutral_name="latitude" arg_name_trans_key="blocks.location.get_current_location.latitude" old_arg_name="latitude" is_detached_parameter="true"/></block></value><value name="field_input2"><block type="callback_arg" id="+(kU0#$^D)X,/HeXec94"><mutation xmlns="http://www.w3.org/1999/xhtml" tooltip="" language_neutral_name="longitude" arg_name_trans_key="blocks.location.get_current_location.longitude" old_arg_name="longitude" is_detached_parameter="true"/></block></value></block></value><next><block type="variables_set_dynamic" id="xKK/=}PU|sW)Btk2z^I)"><field name="SCOPE">CLOUD</field><value name="NAME"><shadow type="text" id="JiNZ3*Vr9@@9I~T:@07V"><field name="TEXT">name</field></shadow><block type="text_join" id="^kOl!z`_PiRolspvOO_3"><mutation items="2"/><value name="ADD0"><block type="variables_get" id="n#xNfW}/s`@?|altue~%"><mutation xmlns="http://www.w3.org/1999/xhtml" saved_name="app variable userID"/><field name="VAR">f1725fbe-2b54-4de7-b810-bb13dc99a163</field></block></value><value name="ADD1"><block type="text" id="`YMnsS/ICi`~Zgpl8)N{"><field name="TEXT">/coordinates</field></block></value></block></value><value name="VALUE"><block type="variables_get" id="aH,s41]Wqu$^35]kAEZk"><mutation xmlns="http://www.w3.org/1999/xhtml" saved_name="app variable loc_points"/><field name="VAR">365a594e-a113-4f6a-a43d-85a9c24d0059</field></block></value></block></next></block></statement></block></next></block></statement><next><block type="caller" id="`5tIVF(9bAE0I*Y?cyL(" inline="false"><mutation xmlns="http://www.w3.org/1999/xhtml" component_name="Timer1" component_id="31d61962-5b2f-449f-99bc-301958c6013e" component_type="Timer" function_name="Start" was_updated="true"/><field name="component_id">31d61962-5b2f-449f-99bc-301958c6013e</field><field name="function_name">Start</field><next><block type="setter" id="!zJ;7Z-kJzq{9fY*@kLH"><mutation xmlns="http://www.w3.org/1999/xhtml" component_name="Container1"/><field name="component_id">a563a483-70e4-4bc6-b34b-b05ffef3acd5</field><field name="field_name">BackgroundColor</field><value name="field_value"><shadow type="colour_picker" id="I1Z%s|GieF{Na19V}*^h"><field name="COLOUR">#000000</field></shadow><block type="variables_get" id="KpzQr6;KudjY1]Yv`K?{"><mutation xmlns="http://www.w3.org/1999/xhtml" saved_name="app variable app_color"/><field name="VAR">12ad059a-0bbd-45c0-8d1d-ca44732b9e89</field></block></value><next><block type="location_get_current_location" id="D@)trjj2xF|evC[MyART"><mutation xmlns="http://www.w3.org/1999/xhtml" show_callback_params="true" callback_params_added="true"/><value name="CALLBACK_PARAM0"><block type="callback_arg" id="XPX^*(3Fx,#=sGENSWP_"><mutation xmlns="http://www.w3.org/1999/xhtml" tooltip="" language_neutral_name="latitude" arg_name_trans_key="blocks.location.get_current_location.latitude" old_arg_name="latitude"/></block></value><value name="CALLBACK_PARAM1"><block type="callback_arg" id="N/g|R1|A70~Ojw~cS{hu"><mutation xmlns="http://www.w3.org/1999/xhtml" tooltip="" language_neutral_name="longitude" arg_name_trans_key="blocks.location.get_current_location.longitude" old_arg_name="longitude"/></block></value><value name="CALLBACK_PARAM2"><block type="callback_arg" id="$}4Iyd`u{-,TpMFSfqfJ"><mutation xmlns="http://www.w3.org/1999/xhtml" tooltip="" language_neutral_name="location" arg_name_trans_key="blocks.location.get_current_location.location" old_arg_name="location"/></block></value><value name="CALLBACK_PARAM3"><block type="callback_arg" id="LPcGIy!sS.QG^54l1!?7"><mutation xmlns="http://www.w3.org/1999/xhtml" tooltip="" language_neutral_name="error" arg_name_trans_key="blocks.location.error" old_arg_name="error"/></block></value><statement name="DO"><block type="setter" id="H;g`D[dVjqbWz!Kz`4yS"><mutation xmlns="http://www.w3.org/1999/xhtml" component_name="Map1"/><field name="component_id">c37ecc80-7e3f-4d96-a908-ca5976d988bf</field><field name="field_name">Latitude</field><value name="field_value"><shadow type="math_number" id="FU_#mu-|*L+b~^!O39j_"><field name="NUM">37.78</field></shadow><block type="callback_arg" id="C$_Nj[#arpng{$Q^~EB2"><mutation xmlns="http://www.w3.org/1999/xhtml" tooltip="" language_neutral_name="latitude" arg_name_trans_key="blocks.location.get_current_location.latitude" old_arg_name="latitude" is_detached_parameter="true"/></block></value><next><block type="setter" id="~J`!l1e8;~1YpfF3r*sS"><mutation xmlns="http://www.w3.org/1999/xhtml" component_name="Map1"/><field name="component_id">c37ecc80-7e3f-4d96-a908-ca5976d988bf</field><field name="field_name">Longitude</field><value name="field_value"><shadow type="math_number" id="-{*(^$D`F:Fi(?wloA!k"><field name="NUM">-122.4</field></shadow><block type="callback_arg" id="612T}{/UsfqCfOS}XA?z"><mutation xmlns="http://www.w3.org/1999/xhtml" tooltip="" language_neutral_name="longitude" arg_name_trans_key="blocks.location.get_current_location.longitude" old_arg_name="longitude" is_detached_parameter="true"/></block></value></block></next></block></statement></block></next></block></next></block></next></block></statement></block><block type="component_event" id="WUH7+Fp$X/ii=n^_hbwK" x="1046" y="23"><mutation xmlns="http://www.w3.org/1999/xhtml" component_id="6a061b70-3848-4501-a07f-bd53fd74d617" component_name="GalleryIcon" component_type="Image" parent_id="undefined" event_id="Click" was_updated="true"/><field name="component_id">6a061b70-3848-4501-a07f-bd53fd74d617</field><field name="event_id">Click</field><statement name="input_do"><block type="controls_navigate_new" id="s*Yo0TKq|$!_ybs2{510"><value name="COMPONENT"><shadow type="any_component_component_dropdown" id="Oj+Rm5?TFQHQ_h`=!OwK"><mutation xmlns="http://www.w3.org/1999/xhtml" component_id="Gallery" component_types_to_include="[&quot;Screen&quot;]"/><field name="component_id">f2a5151e-bc0b-4c6f-b4d6-2cf44963f8b9</field></shadow></value></block></statement></block><block type="component_event" id=")uy1=*W1c#;/G%-uMO#$" x="1042" y="120"><mutation xmlns="http://www.w3.org/1999/xhtml" component_id="cb707565-3410-47a8-a74b-866173cc3d20" component_name="MapIcon" component_type="Image" parent_id="undefined" event_id="Click" was_updated="true"/><field name="component_id">cb707565-3410-47a8-a74b-866173cc3d20</field><field name="event_id">Click</field><statement name="input_do"><block type="controls_navigate_new" id="?/x#UO67;]8Y6fImBMuI"><value name="COMPONENT"><shadow type="any_component_component_dropdown" id="eXi_YZG`;?|t[DPDlc=E"><mutation xmlns="http://www.w3.org/1999/xhtml" component_id="Map" component_types_to_include="[&quot;Screen&quot;]"/><field name="component_id">06028a38-f9c7-4ca2-87c9-7242635840d6</field></shadow></value></block></statement></block><block type="component_event" id="`k7MBd}8g6451]b;ddqN" x="1042" y="231"><mutation xmlns="http://www.w3.org/1999/xhtml" component_id="6ffeeeee-f3b5-421c-b479-fcdc77c2d6d6" component_name="ProfileIcon" component_type="Image" parent_id="undefined" event_id="Click" was_updated="true"/><field name="component_id">6ffeeeee-f3b5-421c-b479-fcdc77c2d6d6</field><field name="event_id">Click</field><statement name="input_do"><block type="controls_navigate_new" id="pfsMza#SZ`1Xz+Otk?c,"><value name="COMPONENT"><shadow type="any_component_component_dropdown" id="l,O(.ID1U5I?Rq||l7#["><mutation xmlns="http://www.w3.org/1999/xhtml" component_id="Profile" component_types_to_include="[&quot;Screen&quot;]"/><field name="component_id">570fd745-230f-4980-b826-5589907e6dc5</field></shadow></value></block></statement></block><block type="component_event" id="Zc-2Sm5**~E;etJsUwsX" x="1037" y="345"><mutation xmlns="http://www.w3.org/1999/xhtml" component_id="1fe5bf1e-0f36-4a4a-957d-e0f43dacd040" component_name="CameraIcon" component_type="Image" parent_id="undefined" event_id="Click" was_updated="true"/><field name="component_id">1fe5bf1e-0f36-4a4a-957d-e0f43dacd040</field><field name="event_id">Click</field><statement name="input_do"><block type="controls_navigate_new" id="L./MVvvsU*lEt(se}$H%"><value name="COMPONENT"><shadow type="any_component_component_dropdown" id="cZ,:U1k~oyAj]p`^dcTC"><mutation xmlns="http://www.w3.org/1999/xhtml" component_id="Camera" component_types_to_include="[&quot;Screen&quot;]"/><field name="component_id">a8843067-b0cc-4362-81bb-e50742a3fbca</field></shadow></value></block></statement></block><block type="component_event" id="%[Nvn;$c+l-.|(:[V-}E" x="105" y="959"><mutation xmlns="http://www.w3.org/1999/xhtml" component_id="31d61962-5b2f-449f-99bc-301958c6013e" component_name="Timer1" component_type="Timer" parent_id="undefined" event_id="Fires" was_updated="true"/><field name="component_id">31d61962-5b2f-449f-99bc-301958c6013e</field><field name="event_id">Fires</field><statement name="input_do"><block type="location_get_current_location" id="UP:/Rd{O}bJ`vM${WWwq"><mutation xmlns="http://www.w3.org/1999/xhtml" show_callback_params="true" callback_params_added="true"/><value name="CALLBACK_PARAM0"><block type="callback_arg" id=")bNe.4ytkc|Fsc4Fo~zf"><mutation xmlns="http://www.w3.org/1999/xhtml" tooltip="" language_neutral_name="latitude" arg_name_trans_key="blocks.location.get_current_location.latitude" old_arg_name="latitude"/></block></value><value name="CALLBACK_PARAM1"><block type="callback_arg" id="6FJkLnc,nG-yVO9Mt,@o"><mutation xmlns="http://www.w3.org/1999/xhtml" tooltip="" language_neutral_name="longitude" arg_name_trans_key="blocks.location.get_current_location.longitude" old_arg_name="longitude"/></block></value><value name="CALLBACK_PARAM2"><block type="callback_arg" id="vGCH^lvB[%uL/0*v[23("><mutation xmlns="http://www.w3.org/1999/xhtml" tooltip="" language_neutral_name="location" arg_name_trans_key="blocks.location.get_current_location.location" old_arg_name="location"/></block></value><value name="CALLBACK_PARAM3"><block type="callback_arg" id="quzUrL~;l8QEnfs~ki.R"><mutation xmlns="http://www.w3.org/1999/xhtml" tooltip="" language_neutral_name="error" arg_name_trans_key="blocks.location.error" old_arg_name="error"/></block></value><statement name="DO"><block type="lists_setIndex" id=",R*d+yi2jYF1TL2dmhy^"><mutation at="false"/><field name="MODE">INSERT</field><field name="WHERE">LAST</field><value name="LIST"><block type="variables_get" id="q7cdo/W|l=Hhp1?*d%%^"><mutation xmlns="http://www.w3.org/1999/xhtml" saved_name="app variable loc_points"/><field name="VAR">365a594e-a113-4f6a-a43d-85a9c24d0059</field></block></value><value name="TO"><shadow type="text" id="%U.0FOSdcc;9u}rMzM`D"><field name="TEXT">abc</field></shadow><block type="object_create" id="E-F_bWm)Z#OTO%~PJ@X5"><mutation xmlns="http://www.w3.org/1999/xhtml" num_fields="2"><field name="latitude"/><field name="longitude"/></mutation><field name="field1">latitude</field><field name="field2">longitude</field><value name="field_input1"><block type="callback_arg" id="2;?BLtpr(g?DO#fP8y=b"><mutation xmlns="http://www.w3.org/1999/xhtml" tooltip="" language_neutral_name="latitude" arg_name_trans_key="blocks.location.get_current_location.latitude" old_arg_name="latitude" is_detached_parameter="true"/></block></value><value name="field_input2"><block type="callback_arg" id="5?*W~|PFu!~aRcaa!ij|"><mutation xmlns="http://www.w3.org/1999/xhtml" tooltip="" language_neutral_name="longitude" arg_name_trans_key="blocks.location.get_current_location.longitude" old_arg_name="longitude" is_detached_parameter="true"/></block></value></block></value><next><block type="variables_set_dynamic" id="P%a4R%I^(pm9hjM}8z$M"><field name="SCOPE">CLOUD</field><value name="NAME"><shadow type="text" id="c2^R#`ozm_jmRj/9-*ql"><field name="TEXT">name</field></shadow><block type="text_join" id="F123-{2xjE%A@)2GAKEn"><mutation items="2"/><value name="ADD0"><block type="variables_get" id="L6cUqn:Jvqq[Zg`cKzr1"><mutation xmlns="http://www.w3.org/1999/xhtml" saved_name="app variable userID"/><field name="VAR">f1725fbe-2b54-4de7-b810-bb13dc99a163</field></block></value><value name="ADD1"><block type="text" id="eRa49Z+jrl?fDUw_fv@D"><field name="TEXT">/coordinates</field></block></value></block></value><value name="VALUE"><block type="variables_get" id="OmW|XG7QD,fe(s^Qy.x!"><mutation xmlns="http://www.w3.org/1999/xhtml" saved_name="app variable loc_points"/><field name="VAR">365a594e-a113-4f6a-a43d-85a9c24d0059</field></block></value><next><block type="caller" id="f`b*c)7no47[BLJB*i%4" inline="false"><mutation xmlns="http://www.w3.org/1999/xhtml" component_name="Map1" component_id="c37ecc80-7e3f-4d96-a908-ca5976d988bf" component_type="Map" function_name="addPolyline" was_updated="true"/><field name="component_id">c37ecc80-7e3f-4d96-a908-ca5976d988bf</field><field name="function_name">addPolyline</field><value name="arg0"><block type="lists_getSublist" id="fAHRND1AH{;mxm}:26*~"><mutation at1="true" at2="false"/><field name="WHERE1">FROM_END</field><field name="WHERE2">LAST</field><value name="LIST"><block type="variables_get" id="WH(7gsR:l!b(!6[PdT^A"><mutation xmlns="http://www.w3.org/1999/xhtml" saved_name="app variable loc_points"/><field name="VAR">365a594e-a113-4f6a-a43d-85a9c24d0059</field></block></value><value name="AT1"><shadow type="math_number" id="]VhcOuy*?9GOB@je-b{Y"><field name="NUM">3</field></shadow></value></block></value><value name="arg1"><shadow type="math_number" id="ZbM$-g6uRU!X%dBO/et+"><field name="NUM">3</field></shadow><block type="variables_get" id="ch;)j^t8Vv]p3~7Ku*xr"><mutation xmlns="http://www.w3.org/1999/xhtml" saved_name="app variable line_width"/><field name="VAR">953b3a73-0489-44c5-bbd5-29f1d4a513d3</field></block></value><value name="arg2"><shadow type="text" id="D.TNy~wZHlaTups?:zSm"><field name="TEXT"/></shadow><block type="variables_get" id=".p#%5X3etgj;x{_e_`AZ"><mutation xmlns="http://www.w3.org/1999/xhtml" saved_name="app variable line_color"/><field name="VAR">b05387ac-6063-4c72-8859-f99d94d37c1d</field></block></value></block></next></block></next></block></statement></block></statement></block><block type="variables_def" id="^mMn(!5?1}wtj{vfde9y" x="1047" y="1028"><mutation xmlns="http://www.w3.org/1999/xhtml" no_input="false" variable_uuid="953b3a73-0489-44c5-bbd5-29f1d4a513d3" variable_name="line_width" variable_scope="APP"/><field name="SCOPE">APP</field><field name="NAME">line_width</field><value name="VALUE"><block type="math_number" id="~ZW=?~I+HkP?Ak%4UqD2"><field name="NUM">3</field></block></value></block><block type="variables_def" id="z9u$;I-Br~*?A^jvTrfN" x="1065" y="1084"><mutation xmlns="http://www.w3.org/1999/xhtml" no_input="false" variable_uuid="b05387ac-6063-4c72-8859-f99d94d37c1d" variable_name="line_color" variable_scope="APP"/><field name="SCOPE">APP</field><field name="NAME">line_color</field><value name="VALUE"><block type="colour_picker" id="$3=lL4AOAoWSP2/3]3ku"><field name="COLOUR">#ff0000</field></block></value></block></xml>